vcjabc/__init__.py
vcjabc-0.0.99.dist-info/WHEEL
vcjabc-0.0.99.dist-info/METADATA
vcjabc-0.0.99.dist-info/RECORD
