Metadata-Version: 2.4
Name: vcjabc
Version: 0.0.99
Summary: Deleted
Author-email: No <no@thankx.com>
Requires-Python: >=3.8
Classifier: Development Status :: 4 - Beta
Classifier: Programming Language :: Python :: 3
Classifier: Programming Language :: Python :: 3.8
Classifier: Programming Language :: Python :: 3.9
Classifier: Programming Language :: Python :: 3.10
Classifier: Operating System :: OS Independent
